Practice/LAB8/fsm.v
`timescale 1ns/100ps

module fsm (input wire clk, rst, input_sig, output wire out);
reg [3:0] state, next_state;
parameter S0 = 0, S1 = 1, S2 = 2, S3 = 3;

assign out = (state[S3]);

always @ (posedge clk or posedge rst )
    if (rst)
        state <= #1 4'b0001; // S0 the initial state
    else
        state <= #1 next_state;

always @ (state or input_sig)
begin
    next_state = 4'b0000;
    case (1'b1)
        state [S0]:
            if(input_sig)
                next_state [S1] = 1'b1;
            else
                next_state [S0] = 1'b1;
        state [S1]:
            if(input_sig)
                next_state [S2] = 1'b1;
            else
                next_state [S0] = 1'b1;
		state [S2]:
            if(!input_sig)
                next_state [S3] = 1'b1;
            else
                next_state [S2] = 1'b1;
        state [S3]:
		    if(input_sig)
                next_state [S1] = 1'b1;
            else
                next_state [S0] = 1'b1;
        default:
            next_state [S0] = 1'b1;
    endcase
end
endmodule

Practice/LAB8/fsm_tb.v
`timescale 1ns/100ps

module fsm_tb();
    
    reg clk, rst, input_sig;
    wire out;
    
    fsm dut (
    .clk(clk),
    .rst(rst),
    .input_sig(input_sig),
    .out(out)
    );
    
    initial begin
        $dumpfile("wave.vcd"); //生成的vcd文件名称
        $dumpvars(0, fsm_tb); //tb模块名称
    end
    
    initial begin
        clk = 0;
        repeat(20)begin
            #5 clk = ~clk;
        end
    end
    
    initial begin
        rst       = 1;
        input_sig = 0;
        #10 rst   = 0;
    end
    
    initial begin
        #20 input_sig = 1;
        #10 input_sig = 1;
        #10 input_sig = 0;
    end
endmodule

Practice/LAB8/wave.vcd
$date
	Fri Apr 28 23:12:57 2023
$end
$version
	Icarus Verilog
$end
$timescale
	100ps
$end
$scope module fsm_tb $end
$var wire 1 ! out $end
$var reg 1 " clk $end
$var reg 1 # input_sig $end
$var reg 1 $ rst $end
$scope module dut $end
$var wire 1 " clk $end
$var wire 1 # input_sig $end
$var wire 1 $ rst $end
$var wire 1 ! out $end
$var reg 4 % next_state [3:0] $end
$var reg 4 & state [3:0] $end
$upscope $end
$upscope $end
$enddefinitions $end
#0
$dumpvars
bx &
b1 %
1$
0#
0"
x!
$end
#10
b1 %
0!
b1 &
#50
1"
#100
0"
0$
#150
1"
#200
b10 %
0"
1#
#250
1"
#260
b100 %
b10 &
#300
0"
#350
1"
#360
b100 %
b100 &
#400
b1000 %
0"
0#
#450
1"
#460
b1 %
1!
b1000 &
#500
0"
#550
1"
#560
b1 %
0!
b1 &
