Practice/LAB6/test.v
module test (clk, rst, op, A, B, Z);
input clk;
input rst;
input [1:0] op;
input [2:0] A;
input [2:0] B;
output reg [2:0] Z;

always @(posedge clk or negedge rst)
begin
	if(~rst)begin
		Z <= 3'b000;
	end
	else begin
		case (op)
			2'b00 : Z <= A + B;
			2'b01 : Z <= A - B;
			2'b10 : Z <= A & B;
			2'b11 : Z <= A | B;
		endcase
	end
end

endmodule

Practice/LAB6/test_tb.v
`timescale 1ns/100ps
module test_tb();
    reg clk;
    reg rst;
    reg  [1:0]  op;
    reg  [2:0] A,B,Zexpected;
    wire [2:0]   Z;
    reg  [31:0] vectornum, errors;
    reg  [10:0]  testvectors[10000:0];
    // instantiate device under test
    test test(clk, rst, op, A, B, Z);
    
    initial
    begin
        clk = 0;
        rst = 1;
        $dumpfile ("dump.vcd");
        $dumpvars;
    end
    
    initial begin
        clk = 0;
        repeat(20)begin
            #1 clk = ~clk;
        end
    end
    
    initial
    begin
        
        $readmemb("example.tv", testvectors);
        vectornum = 0; errors = 0;
        repeat(10) begin
            #1;
            {op,A,B,Zexpected} = testvectors[vectornum];
            #1;
            if (Z !== Zexpected) begin
                $display("Error: inputs = %b", {op,A,B});
                $display("  outputs     = %b (%b expected)", Z, Zexpected);
                errors                  = errors + 1;
            end
            
            vectornum = vectornum + 1;
            if (testvectors[vectornum] === 10'bx) begin
                $display("%d tests completed with %d errors", vectornum, errors);
                #10  $stop;
            end
        end
    end
endmodule

Practice/LAB6/dump.vcd
$date
	Sat Apr 29 12:33:58 2023
$end
$version
	Icarus Verilog
$end
$timescale
	100ps
$end
$scope module test_tb $end
$var wire 3 ! Z [2:0] $end
$var reg 3 " A [2:0] $end
$var reg 3 # B [2:0] $end
$var reg 3 $ Zexpected [2:0] $end
$var reg 1 % clk $end
$var reg 32 & errors [31:0] $end
$var reg 2 ' op [1:0] $end
$var reg 1 ( rst $end
$var reg 32 ) vectornum [31:0] $end
$scope module test $end
$var wire 3 * A [2:0] $end
$var wire 3 + B [2:0] $end
$var wire 1 % clk $end
$var wire 2 , op [1:0] $end
$var wire 1 ( rst $end
$var reg 3 - Z [2:0] $end
$upscope $end
$upscope $end
$enddefinitions $end
#0
$dumpvars
bx -
bx ,
bx +
bx *
b0 )
1(
bx '
b0 &
0%
bx $
bx #
bx "
bx !
$end
#10
b1 !
b1 -
b10 '
b10 ,
b111 "
b111 *
b1 #
b1 +
b1 $
1%
#20
b1 )
0%
#30
b10 !
b10 -
b1 '
b1 ,
b11 "
b11 *
b10 $
1%
#40
b10 )
0%
#50
b0 !
b0 -
b10 '
b10 ,
b100 "
b100 *
b11 #
b11 +
b0 $
1%
#60
b11 )
0%
#70
b101 !
b101 -
b111 "
b111 *
b101 #
b101 +
b101 $
1%
#80
b100 )
0%
#90
b0 !
b0 -
b10 "
b10 *
b0 #
b0 +
b0 $
1%
#100
b101 )
0%
#110
b1 !
b1 -
b1 "
b1 *
b111 #
b111 +
b1 $
1%
#120
b110 )
0%
#130
b11 !
b11 -
b11 '
b11 ,
b11 "
b11 *
b11 #
b11 +
b11 $
1%
#140
b111 )
0%
#150
b1 !
b1 -
b0 '
b0 ,
b1 "
b1 *
b0 #
b0 +
b1 $
1%
#160
b1000 )
0%
#170
b110 !
b110 -
b10 '
b10 ,
b111 "
b111 *
b110 #
b110 +
b110 $
1%
#180
b1001 )
0%
#190
b10 !
b10 -
b1 '
b1 ,
b101 "
b101 *
b11 #
b11 +
b10 $
1%
#200
b1010 )
0%
